pyxproject/__init__.py
pyxproject/x.py
pyxproject-0.1.dist-info/METADATA
pyxproject-0.1.dist-info/WHEEL
pyxproject-0.1.dist-info/top_level.txt
pyxproject-0.1.dist-info/RECORD
